__init__.py
cdesf/__init__.py
cdesf/clustering/__init__.py
cdesf/clustering/denstream.py
cdesf/core/__init__.py
cdesf/core/cdesf.py
cdesf/data_structures/__init__.py
cdesf/data_structures/case.py
cdesf/data_structures/cluster.py
cdesf/data_structures/micro_cluster.py
cdesf/utils/__init__.py
cdesf/utils/distances.py
cdesf/utils/graph_operations.py
cdesf/utils/metrics.py
cdesf/utils/reading.py
cdesf/visualization/__init__.py
cdesf/visualization/drifts.py
cdesf/visualization/feature_space.py
cdesf/visualization/graphs.py
clustering/__init__.py
clustering/denstream.py
core/__init__.py
core/cdesf.py
data_structures/__init__.py
data_structures/case.py
data_structures/cluster.py
data_structures/micro_cluster.py
tests/__init__.py
tests/conftest.py
tests/test_case.py
tests/test_cdesf.py
tests/test_cluster.py
tests/test_denstream.py
tests/test_distances.py
tests/test_graph_operations.py
tests/test_micro_cluster.py
tests/test_pipeline.py
tests/test_reading.py
tests/test_visualization.py
utils/__init__.py
utils/distances.py
utils/graph_operations.py
utils/metrics.py
utils/reading.py
visualization/__init__.py
visualization/drifts.py
visualization/feature_space.py
visualization/graphs.py
cdesf-0.0.2.dist-info/LICENSE
cdesf-0.0.2.dist-info/METADATA
cdesf-0.0.2.dist-info/WHEEL
cdesf-0.0.2.dist-info/top_level.txt
cdesf-0.0.2.dist-info/RECORD
