Metadata-Version: 2.1
Name: cdesf
Version: 0.0.2
Summary: Concept-drift on Event Stream Framework
Home-page: https://github.com/gbrltv/cdesf2
Author: Gabriel Marques Tavares
License: UNKNOWN
Platform: UNKNOWN
License-File: LICENSE
Requires-Dist: networkx (==2.5)
Requires-Dist: numpy (==1.20.*)
Requires-Dist: pandas (==1.2.*)
Requires-Dist: scipy (==1.6.*)
Requires-Dist: matplotlib (==3.3.*)
Requires-Dist: seaborn (==0.11.*)
Requires-Dist: pydot (==1.4.*)
Requires-Dist: pydot-ng (==2.0.*)
Requires-Dist: pygraphviz (==1.7)
Requires-Dist: pm4py (==2.2.*)
